src/lab1/traffic_light.v
module traffic_light (clk, rst, pass, R, G, Y);

//write your code here
input clk, rst, pass;
output reg R;
output reg G;
output reg Y;


reg [2:0] state; // 7 states
// num : state   cycles
// 000 : Green 1024cycles
// 001 : None  128cycles
// 010 : Green 128cycles
// 011 : None  128cycles
// 100 : Green 128cycles
// 101 : Yello 512cycles
// 110 : Red   1024cycles

reg [10:0] cycle; // max 2047 cycles but we need 1024, so using 11 bit for this reg

always@(posedge clk or posedge rst) begin //

  if (rst) begin
      R <= 0;
      G <= 1;
      Y <= 0;
      state <= 3'd0;
      cycle <= 11'd1;
  end

  else if (pass) begin
      if (state != 3'd0) begin
        R <= 0;
        G <= 1;
        Y <= 0;
        state <= 3'd0;
        cycle <= 11'd1;
      end
      else cycle <= cycle + 11'd1;
  end

  else begin

    cycle <= cycle + 11'd1;

    if (state == 3'd0) begin // 000 for Green 1024 cycles
      R <= 0;
      G <= 1;
      Y <= 0;
      if (cycle == 11'd1023) begin
        state <= 3'd1;
        cycle <= 11'd0;
      end
    end

    else if (state == 3'd1) begin //001 for none 128 cycles
      R <= 0;
      G <= 0;
      Y <= 0;
      if (cycle == 11'd127) begin
        state <= 3 'd2;
        cycle <= 11'd0;
      end
    end

    else if (state == 3'd2) begin //010 for Green 128 cycles
      R <= 0;
      G <= 1;
      Y <= 0;
      if (cycle == 11'd127) begin
        state <= 3'd3;
        cycle <= 11'd0;
      end
    end

    else if (state == 3'd3) begin //011 for none 128 cycles
      R <= 0;
      G <= 0;
      Y <= 0;
      if (cycle == 11'd127) begin
        state <= 3'd4;
        cycle <= 11'd0;
      end
    end

    else if (state == 3'd4) begin //100 for Green 128 cycles
      R <= 0;
      G <= 1;
      Y <= 0;
      if (cycle == 11'd127) begin
        state <= 3'd5;
        cycle <= 11'd0;
      end
    end

    else if (state == 3'd5) begin //101 for Yellow 512 cycles
      R <= 0;
      G <= 0;
      Y <= 1;
      if (cycle == 11'd511) begin
        state <= 3'd6;
        cycle <= 11'd0;
      end
    end

    else if (state == 3'd6) begin //110 for Red 1024cycles
      R <= 1;
      G <= 0;
      Y <= 0;
      if (cycle == 11'd1023) begin
        state <= 3'd0;
        cycle <= 11'd0;
      end
    end

  end
end

endmodule

src/lab1/traffic_light_tb.v
`timescale 1ns/10ps

`define ANSTXT "ans.txt"
`define TOTAL_CYCLES 8192
`define CYCLE 10

module traffic_light_tb;

reg        sysclk;
reg        rst;
reg        pass;
wire       R, 
           G, 
           Y;
 
reg  [ 2:0] ans [8191:0];
wire [ 2:0] out;
 
reg  [15:0] count;
reg         start;
reg         fin;

integer error;

// DUV
traffic_light ul(
    .clk  ( sysclk ),
    .rst  ( rst    ),
    .pass ( pass   ),
    .R	  ( R      ),
    .G	  ( G      ),
    .Y	  ( Y      )
);

always #(`CYCLE / 2) sysclk = ~sysclk;

// Wave
initial begin

    $dumpfile("homework1.vcd");
    $dumpvars;

end

// Initialization
initial begin
    sysclk = 1'b0;
    pass   = 1'b0;
    error  = 32'b0;
    start  = 1'b0;
    count  = 16'b0;
end

// Reset signal
initial begin
    rst    = 1'b0;
    #1      rst = 1'b1;
    #`CYCLE rst = 1'b0;
end

initial begin
    #(`CYCLE * 1792) 
    @(negedge sysclk)
        pass = 1'b1;
    #(`CYCLE)
        pass = 1'b0;
    #(`CYCLE * 512) 
    @(negedge sysclk)
        pass = 1'b1;
    #(`CYCLE)
        pass = 1'b0;
end

initial begin
    $readmemb(`ANSTXT, ans);
    fin = 0;
    #(`TOTAL_CYCLES * `CYCLE);
    fin = 1;
    #1;
    $finish;
end

always @(posedge sysclk) begin
    if(rst) start <= 1'b1;
    else    start <= start;
end

assign out = ans[count];

always @(posedge sysclk) begin
    if(rst) begin
        count <= 16'b0;
    end
    else begin
        count <= count + 16'b1;
    end
end

always @(negedge sysclk) begin
    if(start & ~fin) begin
        if (out[2] !== R || 
            out[1] !== G ||
            out[0] !== Y) begin
            $write("Error at %0dth cycle:\n", count);
            $write("Real answer: R = %d ,G = %d ,Y = %d\n", out[2], out[1], out[0]);
            $write("Your answer: R = %d ,G = %d ,Y = %d\n", R, G, Y);
            error = error + 1;
        end
    end
end


always @(posedge fin) begin
    if(error) begin
        $display("\n");
        $display("====================================================================================");
        $display("-------------- (/`n`)/ ~#  There was %2d errors in your code !! ---------------------",error); 
        $display("--------- The simulation has finished with some error, Please check it !!! ---------"); 
        $display("====================================================================================");
        $display("\n");
    end
    else begin
        $display("\n");
        $display("        ****************************               ");
        $display("        **                        **       /|__/|  ");
        $display("        **  Congratulations !!    **      / O,O  | ");
        $display("        **                        **    /_____   | ");
        $display("        **  Simulation PASS!!     **   /^ ^ ^ \\  |");
        $display("        **                        **  |^ ^ ^ ^ |w| ");
        $display("        *************** ************   \\m___m__|_|");
        $display("\n");
    end
end

endmodule

src/lab1/homework1.vcd
$date
	Mon Mar 15 15:57:14 2021
$end
$version
	Icarus Verilog
$end
$timescale
	10ps
$end
$scope module traffic_light_tb $end
$var wire 3 ! out [2:0] $end
$var wire 1 " Y $end
$var wire 1 # R $end
$var wire 1 $ G $end
$var reg 16 % count [15:0] $end
$var reg 1 & fin $end
$var reg 1 ' pass $end
$var reg 1 ( rst $end
$var reg 1 ) start $end
$var reg 1 * sysclk $end
$var integer 32 + error [31:0] $end
$scope module ul $end
$var wire 1 * clk $end
$var wire 1 ' pass $end
$var wire 1 ( rst $end
$var reg 1 $ G $end
$var reg 1 # R $end
$var reg 1 " Y $end
$var reg 11 , cycle [10:0] $end
$var reg 3 - state [2:0] $end
$upscope $end
$upscope $end
$enddefinitions $end
#0
$dumpvars
bx -
bx ,
b0 +
0*
0)
0(
0'
0&
b0 %
x$
x#
x"
b10 !
$end
#100
b1 ,
b0 -
0"
1$
0#
1(
#500
1)
1*
#1000
0*
#1100
0(
#1500
b10 ,
b1 %
1*
#2000
0*
#2500
b11 ,
b10 %
1*
#3000
0*
#3500
b100 ,
b11 %
1*
#4000
0*
#4500
b101 ,
b100 %
1*
#5000
0*
#5500
b110 ,
b101 %
1*
#6000
0*
#6500
b111 ,
b110 %
1*
#7000
0*
#7500
b1000 ,
b111 %
1*
#8000
0*
#8500
b1001 ,
b1000 %
1*
#9000
0*
#9500
b1010 ,
b1001 %
1*
#10000
0*
#10500
b1011 ,
b1010 %
1*
#11000
0*
#11500
b1100 ,
b1011 %
1*
#12000
0*
#12500
b1101 ,
b1100 %
1*
#13000
0*
#13500
b1110 ,
b1101 %
1*
#14000
0*
#14500
b1111 ,
b1110 %
1*
#15000
0*
#15500
b10000 ,
b1111 %
1*
#16000
0*
#16500
b10001 ,
b10000 %
1*
#17000
0*
#17500
b10010 ,
b10001 %
1*
#18000
0*
#18500
b10011 ,
b10010 %
1*
#19000
0*
#19500
b10100 ,
b10011 %
1*
#20000
0*
#20500
b10101 ,
b10100 %
1*
#21000
0*
#21500
b10110 ,
b10101 %
1*
#22000
0*
#22500
b10111 ,
b10110 %
1*
#23000
0*
#23500
b11000 ,
b10111 %
1*
#24000
0*
#24500
b11001 ,
b11000 %
1*
#25000
0*
#25500
b11010 ,
b11001 %
1*
#26000
0*
#26500
b11011 ,
b11010 %
1*
#27000
0*
#27500
b11100 ,
b11011 %
1*
#28000
0*
#28500
b11101 ,
b11100 %
1*
#29000
0*
#29500
b11110 ,
b11101 %
1*
#30000
0*
#30500
b11111 ,
b11110 %
1*
#31000
0*
#31500
b100000 ,
b11111 %
1*
#32000
0*
#32500
b100001 ,
b100000 %
1*
#33000
0*
#33500
b100010 ,
b100001 %
1*
#34000
0*
#34500
b100011 ,
b100010 %
1*
#35000
0*
#35500
b100100 ,
b100011 %
1*
#36000
0*
#36500
b100101 ,
b100100 %
1*
#37000
0*
#37500
b100110 ,
b100101 %
1*
#38000
0*
#38500
b100111 ,
b100110 %
1*
#39000
0*
#39500
b101000 ,
b100111 %
1*
#40000
0*
#40500
b101001 ,
b101000 %
1*
#41000
0*
#41500
b101010 ,
b101001 %
1*
#42000
0*
#42500
b101011 ,
b101010 %
1*
#43000
0*
#43500
b101100 ,
b101011 %
1*
#44000
0*
#44500
b101101 ,
b101100 %
1*
#45000
0*
#45500
b101110 ,
b101101 %
1*
#46000
0*
#46500
b101111 ,
b101110 %
1*
#47000
0*
#47500
b110000 ,
b101111 %
1*
#48000
0*
#48500
b110001 ,
b110000 %
1*
#49000
0*
#49500
b110010 ,
b110001 %
1*
#50000
0*
#50500
b110011 ,
b110010 %
1*
#51000
0*
#51500
b110100 ,
b110011 %
1*
#52000
0*
#52500
b110101 ,
b110100 %
1*
#53000
0*
#53500
b110110 ,
b110101 %
1*
#54000
0*
#54500
b110111 ,
b110110 %
1*
#55000
0*
#55500
b111000 ,
b110111 %
1*
#56000
0*
#56500
b111001 ,
b111000 %
1*
#57000
0*
#57500
b111010 ,
b111001 %
1*
#58000
0*
#58500
b111011 ,
b111010 %
1*
#59000
0*
#59500
b111100 ,
b111011 %
1*
#60000
0*
#60500
b111101 ,
b111100 %
1*
#61000
0*
#61500
b111110 ,
b111101 %
1*
#62000
0*
#62500
b111111 ,
b111110 %
1*
#63000
0*
#63500
b1000000 ,
b111111 %
1*
#64000
0*
#64500
b1000001 ,
b1000000 %
1*
#65000
0*
#65500
b1000010 ,
b1000001 %
1*
#66000
0*
#66500
b1000011 ,
b1000010 %
1*
#67000
0*
#67500
b1000100 ,
b1000011 %
1*
#68000
0*
#68500
b1000101 ,
b1000100 %
1*
#69000
0*
#69500
b1000110 ,
b1000101 %
1*
#70000
0*
#70500
b1000111 ,
b1000110 %
1*
#71000
0*
#71500
b1001000 ,
b1000111 %
1*
#72000
0*
#72500
b1001001 ,
b1001000 %
1*
#73000
0*
#73500
b1001010 ,
b1001001 %
1*
#74000
0*
#74500
b1001011 ,
b1001010 %
1*
#75000
0*
#75500
b1001100 ,
b1001011 %
1*
#76000
0*
#76500
b1001101 ,
b1001100 %
1*
#77000
0*
#77500
b1001110 ,
b1001101 %
1*
#78000
0*
#78500
b1001111 ,
b1001110 %
1*
#79000
0*
#79500
b1010000 ,
b1001111 %
1*
#80000
0*
#80500
b1010001 ,
b1010000 %
1*
#81000
0*
#81500
b1010010 ,
b1010001 %
1*
#82000
0*
#82500
b1010011 ,
b1010010 %
1*
#83000
0*
#83500
b1010100 ,
b1010011 %
1*
#84000
0*
#84500
b1010101 ,
b1010100 %
1*
#85000
0*
#85500
b1010110 ,
b1010101 %
1*
#86000
0*
#86500
b1010111 ,
b1010110 %
1*
#87000
0*
#87500
b1011000 ,
b1010111 %
1*
#88000
0*
#88500
b1011001 ,
b1011000 %
1*
#89000
0*
#89500
b1011010 ,
b1011001 %
1*
#90000
0*
#90500
b1011011 ,
b1011010 %
1*
#91000
0*
#91500
b1011100 ,
b1011011 %
1*
#92000
0*
#92500
b1011101 ,
b1011100 %
1*
#93000
0*
#93500
b1011110 ,
b1011101 %
1*
#94000
0*
#94500
b1011111 ,
b1011110 %
1*
#95000
0*
#95500
b1100000 ,
b1011111 %
1*
#96000
0*
#96500
b1100001 ,
b1100000 %
1*
#97000
0*
#97500
b1100010 ,
b1100001 %
1*
#98000
0*
#98500
b1100011 ,
b1100010 %
1*
#99000
0*
#99500
b1100100 ,
b1100011 %
1*
#100000
0*
#100500
b1100101 ,
b1100100 %
1*
#101000
0*
#101500
b1100110 ,
b1100101 %
1*
#102000
0*
#102500
b1100111 ,
b1100110 %
1*
#103000
0*
#103500
b1101000 ,
b1100111 %
1*
#104000
0*
#104500
b1101001 ,
b1101000 %
1*
#105000
0*
#105500
b1101010 ,
b1101001 %
1*
#106000
0*
#106500
b1101011 ,
b1101010 %
1*
#107000
0*
#107500
b1101100 ,
b1101011 %
1*
#108000
0*
#108500
b1101101 ,
b1101100 %
1*
#109000
0*
#109500
b1101110 ,
b1101101 %
1*
#110000
0*
#110500
b1101111 ,
b1101110 %
1*
#111000
0*
#111500
b1110000 ,
b1101111 %
1*
#112000
0*
#112500
b1110001 ,
b1110000 %
1*
#113000
0*
#113500
b1110010 ,
b1110001 %
1*
#114000
0*
#114500
b1110011 ,
b1110010 %
1*
#115000
0*
#115500
b1110100 ,
b1110011 %
1*
#116000
0*
#116500
b1110101 ,
b1110100 %
1*
#117000
0*
#117500
b1110110 ,
b1110101 %
1*
#118000
0*
#118500
b1110111 ,
b1110110 %
1*
#119000
0*
#119500
b1111000 ,
b1110111 %
1*
#120000
0*
#120500
b1111001 ,
b1111000 %
1*
#121000
0*
#121500
b1111010 ,
b1111001 %
1*
#122000
0*
#122500
b1111011 ,
b1111010 %
1*
#123000
0*
#123500
b1111100 ,
b1111011 %
1*
#124000
0*
#124500
b1111101 ,
b1111100 %
1*
#125000
0*
#125500
b1111110 ,
b1111101 %
1*
#126000
0*
#126500
b1111111 ,
b1111110 %
1*
#127000
0*
#127500
b10000000 ,
b1111111 %
1*
#128000
0*
#128500
b10000001 ,
b10000000 %
1*
#129000
0*
#129500
b10000010 ,
b10000001 %
1*
#130000
0*
#130500
b10000011 ,
b10000010 %
1*
#131000
0*
#131500
b10000100 ,
b10000011 %
1*
#132000
0*
#132500
b10000101 ,
b10000100 %
1*
#133000
0*
#133500
b10000110 ,
b10000101 %
1*
#134000
0*
#134500
b10000111 ,
b10000110 %
1*
#135000
0*
#135500
b10001000 ,
b10000111 %
1*
#136000
0*
#136500
b10001001 ,
b10001000 %
1*
#137000
0*
#137500
b10001010 ,
b10001001 %
1*
#138000
0*
#138500
b10001011 ,
b10001010 %
1*
#139000
0*
#139500
b10001100 ,
b10001011 %
1*
#140000
0*
#140500
b10001101 ,
b10001100 %
1*
#141000
0*
#141500
b10001110 ,
b10001101 %
1*
#142000
0*
#142500
b10001111 ,
b10001110 %
1*
#143000
0*
#143500
b10010000 ,
b10001111 %
1*
#144000
0*
#144500
b10010001 ,
b10010000 %
1*
#145000
0*
#145500
b10010010 ,
b10010001 %
1*
#146000
0*
#146500
b10010011 ,
b10010010 %
1*
#147000
0*
#147500
b10010100 ,
b10010011 %
1*
#148000
0*
#148500
b10010101 ,
b10010100 %
1*
#149000
0*
#149500
b10010110 ,
b10010101 %
1*
#150000
0*
#150500
b10010111 ,
b10010110 %
1*
#151000
0*
#151500
b10011000 ,
b10010111 %
1*
#152000
0*
#152500
b10011001 ,
b10011000 %
1*
#153000
0*
#153500
b10011010 ,
b10011001 %
1*
#154000
0*
#154500
b10011011 ,
b10011010 %
1*
#155000
0*
#155500
b10011100 ,
b10011011 %
1*
#156000
0*
#156500
b10011101 ,
b10011100 %
1*
#157000
0*
#157500
b10011110 ,
b10011101 %
1*
#158000
0*
#158500
b10011111 ,
b10011110 %
1*
#159000
0*
#159500
b10100000 ,
b10011111 %
1*
#160000
0*
#160500
b10100001 ,
b10100000 %
1*
#161000
0*
#161500
b10100010 ,
b10100001 %
1*
#162000
0*
#162500
b10100011 ,
b10100010 %
1*
#163000
0*
#163500
b10100100 ,
b10100011 %
1*
#164000
0*
#164500
b10100101 ,
b10100100 %
1*
#165000
0*
#165500
b10100110 ,
b10100101 %
1*
#166000
0*
#166500
b10100111 ,
b10100110 %
1*
#167000
0*
#167500
b10101000 ,
b10100111 %
1*
#168000
0*
#168500
b10101001 ,
b10101000 %
1*
#169000
0*
#169500
b10101010 ,
b10101001 %
1*
#170000
0*
#170500
b10101011 ,
b10101010 %
1*
#171000
0*
#171500
b10101100 ,
b10101011 %
1*
#172000
0*
#172500
b10101101 ,
b10101100 %
1*
#173000
0*
#173500
b10101110 ,
b10101101 %
1*
#174000
0*
#174500
b10101111 ,
b10101110 %
1*
#175000
0*
#175500
b10110000 ,
b10101111 %
1*
#176000
0*
#176500
b10110001 ,
b10110000 %
1*
#177000
0*
#177500
b10110010 ,
b10110001 %
1*
#178000
0*
#178500
b10110011 ,
b10110010 %
1*
#179000
0*
#179500
b10110100 ,
b10110011 %
1*
#180000
0*
#180500
b10110101 ,
b10110100 %
1*
#181000
0*
#181500
b10110110 ,
b10110101 %
1*
#182000
0*
#182500
b10110111 ,
b10110110 %
1*
#183000
0*
#183500
b10111000 ,
b10110111 %
1*
#184000
0*
#184500
b10111001 ,
b10111000 %
1*
#185000
0*
#185500
b10111010 ,
b10111001 %
1*
#186000
0*
#186500
b10111011 ,
b10111010 %
1*
#187000
0*
#187500
b10111100 ,
b10111011 %
1*
#188000
0*
#188500
b10111101 ,
b10111100 %
1*
#189000
0*
#189500
b10111110 ,
b10111101 %
1*
#190000
0*
#190500
b10111111 ,
b10111110 %
1*
#191000
0*
#191500
b11000000 ,
b10111111 %
1*
#192000
0*
#192500
b11000001 ,
b11000000 %
1*
#193000
0*
#193500
b11000010 ,
b11000001 %
1*
#194000
0*
#194500
b11000011 ,
b11000010 %
1*
#195000
0*
#195500
b11000100 ,
b11000011 %
1*
#196000
0*
#196500
b11000101 ,
b11000100 %
1*
#197000
0*
#197500
b11000110 ,
b11000101 %
1*
#198000
0*
#198500
b11000111 ,
b11000110 %
1*
#199000
0*
#199500
b11001000 ,
b11000111 %
1*
#200000
0*
#200500
b11001001 ,
b11001000 %
1*
#201000
0*
#201500
b11001010 ,
b11001001 %
1*
#202000
0*
#202500
b11001011 ,
b11001010 %
1*
#203000
0*
#203500
b11001100 ,
b11001011 %
1*
#204000
0*
#204500
b11001101 ,
b11001100 %
1*
#205000
0*
#205500
b11001110 ,
b11001101 %
1*
#206000
0*
#206500
b11001111 ,
b11001110 %
1*
#207000
0*
#207500
b11010000 ,
b11001111 %
1*
#208000
0*
#208500
b11010001 ,
b11010000 %
1*
#209000
0*
#209500
b11010010 ,
b11010001 %
1*
#210000
0*
#210500
b11010011 ,
b11010010 %
1*
#211000
0*
#211500
b11010100 ,
b11010011 %
1*
#212000
0*
#212500
b11010101 ,
b11010100 %
1*
#213000
0*
#213500
b11010110 ,
b11010101 %
1*
#214000
0*
#214500
b11010111 ,
b11010110 %
1*
#215000
0*
#215500
b11011000 ,
b11010111 %
1*
#216000
0*
#216500
b11011001 ,
b11011000 %
1*
#217000
0*
#217500
b11011010 ,
b11011001 %
1*
#218000
0*
#218500
b11011011 ,
b11011010 %
1*
#219000
0*
#219500
b11011100 ,
b11011011 %
1*
#220000
0*
#220500
b11011101 ,
b11011100 %
1*
#221000
0*
#221500
b11011110 ,
b11011101 %
1*
#222000
0*
#222500
b11011111 ,
b11011110 %
1*
#223000
0*
#223500
b11100000 ,
b11011111 %
1*
#224000
0*
#224500
b11100001 ,
b11100000 %
1*
#225000
0*
#225500
b11100010 ,
b11100001 %
1*
#226000
0*
#226500
b11100011 ,
b11100010 %
1*
#227000
0*
#227500
b11100100 ,
b11100011 %
1*
#228000
0*
#228500
b11100101 ,
b11100100 %
1*
#229000
0*
#229500
b11100110 ,
b11100101 %
1*
#230000
0*
#230500
b11100111 ,
b11100110 %
1*
#231000
0*
#231500
b11101000 ,
b11100111 %
1*
#232000
0*
#232500
b11101001 ,
b11101000 %
1*
#233000
0*
#233500
b11101010 ,
b11101001 %
1*
#234000
0*
#234500
b11101011 ,
b11101010 %
1*
#235000
0*
#235500
b11101100 ,
b11101011 %
1*
#236000
0*
#236500
b11101101 ,
b11101100 %
1*
#237000
0*
#237500
b11101110 ,
b11101101 %
1*
#238000
0*
#238500
b11101111 ,
b11101110 %
1*
#239000
0*
#239500
b11110000 ,
b11101111 %
1*
#240000
0*
#240500
b11110001 ,
b11110000 %
1*
#241000
0*
#241500
b11110010 ,
b11110001 %
1*
#242000
0*
#242500
b11110011 ,
b11110010 %
1*
#243000
0*
#243500
b11110100 ,
b11110011 %
1*
#244000
0*
#244500
b11110101 ,
b11110100 %
1*
#245000
0*
#245500
b11110110 ,
b11110101 %
1*
#246000
0*
#246500
b11110111 ,
b11110110 %
1*
#247000
0*
#247500
b11111000 ,
b11110111 %
1*
#248000
0*
#248500
b11111001 ,
b11111000 %
1*
#249000
0*
#249500
b11111010 ,
b11111001 %
1*
#250000
0*
#250500
b11111011 ,
b11111010 %
1*
#251000
0*
#251500
b11111100 ,
b11111011 %
1*
#252000
0*
#252500
b11111101 ,
b11111100 %
1*
#253000
0*
#253500
b11111110 ,
b11111101 %
1*
#254000
0*
#254500
b11111111 ,
b11111110 %
1*
#255000
0*
#255500
b100000000 ,
b11111111 %
1*
#256000
0*
#256500
b100000001 ,
b100000000 %
1*
#257000
0*
#257500
b100000010 ,
b100000001 %
1*
#258000
0*
#258500
b100000011 ,
b100000010 %
1*
#259000
0*
#259500
b100000100 ,
b100000011 %
1*
#260000
0*
#260500
b100000101 ,
b100000100 %
1*
#261000
0*
#261500
b100000110 ,
b100000101 %
1*
#262000
0*
#262500
b100000111 ,
b100000110 %
1*
#263000
0*
#263500
b100001000 ,
b100000111 %
1*
#264000
0*
#264500
b100001001 ,
b100001000 %
1*
#265000
0*
#265500
b100001010 ,
b100001001 %
1*
#266000
0*
#266500
b100001011 ,
b100001010 %
1*
#267000
0*
#267500
b100001100 ,
b100001011 %
1*
#268000
0*
#268500
b100001101 ,
b100001100 %
1*
#269000
0*
#269500
b100001110 ,
b100001101 %
1*
#270000
0*
#270500
b100001111 ,
b100001110 %
1*
#271000
0*
#271500
b100010000 ,
b100001111 %
1*
#272000
0*
#272500
b100010001 ,
b100010000 %
1*
#273000
0*
#273500
b100010010 ,
b100010001 %
1*
#274000
0*
#274500
b100010011 ,
b100010010 %
1*
#275000
0*
#275500
b100010100 ,
b100010011 %
1*
#276000
0*
#276500
b100010101 ,
b100010100 %
1*
#277000
0*
#277500
b100010110 ,
b100010101 %
1*
#278000
0*
#278500
b100010111 ,
b100010110 %
1*
#279000
0*
#279500
b100011000 ,
b100010111 %
1*
#280000
0*
#280500
b100011001 ,
b100011000 %
1*
#281000
0*
#281500
b100011010 ,
b100011001 %
1*
#282000
0*
#282500
b100011011 ,
b100011010 %
1*
#283000
0*
#283500
b100011100 ,
b100011011 %
1*
#284000
0*
#284500
b100011101 ,
b100011100 %
1*
#285000
0*
#285500
b100011110 ,
b100011101 %
1*
#286000
0*
#286500
b100011111 ,
b100011110 %
1*
#287000
0*
#287500
b100100000 ,
b100011111 %
1*
#288000
0*
#288500
b100100001 ,
b100100000 %
1*
#289000
0*
#289500
b100100010 ,
b100100001 %
1*
#290000
0*
#290500
b100100011 ,
b100100010 %
1*
#291000
0*
#291500
b100100100 ,
b100100011 %
1*
#292000
0*
#292500
b100100101 ,
b100100100 %
1*
#293000
0*
#293500
b100100110 ,
b100100101 %
1*
#294000
0*
#294500
b100100111 ,
b100100110 %
1*
#295000
0*
#295500
b100101000 ,
b100100111 %
1*
#296000
0*
#296500
b100101001 ,
b100101000 %
1*
#297000
0*
#297500
b100101010 ,
b100101001 %
1*
#298000
0*
#298500
b100101011 ,
b100101010 %
1*
#299000
0*
#299500
b100101100 ,
b100101011 %
1*
#300000
0*
#300500
b100101101 ,
b100101100 %
1*
#301000
0*
#301500
b100101110 ,
b100101101 %
1*
#302000
0*
#302500
b100101111 ,
b100101110 %
1*
#303000
0*
#303500
b100110000 ,
b100101111 %
1*
#304000
0*
#304500
b100110001 ,
b100110000 %
1*
#305000
0*
#305500
b100110010 ,
b100110001 %
1*
#306000
0*
#306500
b100110011 ,
b100110010 %
1*
#307000
0*
#307500
b100110100 ,
b100110011 %
1*
#308000
0*
#308500
b100110101 ,
b100110100 %
1*
#309000
0*
#309500
b100110110 ,
b100110101 %
1*
#310000
0*
#310500
b100110111 ,
b100110110 %
1*
#311000
0*
#311500
b100111000 ,
b100110111 %
1*
#312000
0*
#312500
b100111001 ,
b100111000 %
1*
#313000
0*
#313500
b100111010 ,
b100111001 %
1*
#314000
0*
#314500
b100111011 ,
b100111010 %
1*
#315000
0*
#315500
b100111100 ,
b100111011 %
1*
#316000
0*
#316500
b100111101 ,
b100111100 %
1*
#317000
0*
#317500
b100111110 ,
b100111101 %
1*
#318000
0*
#318500
b100111111 ,
b100111110 %
1*
#319000
0*
#319500
b101000000 ,
b100111111 %
1*
#320000
0*
#320500
b101000001 ,
b101000000 %
1*
#321000
0*
#321500
b101000010 ,
b101000001 %
1*
#322000
0*
#322500
b101000011 ,
b101000010 %
1*
#323000
0*
#323500
b101000100 ,
b101000011 %
1*
#324000
0*
#324500
b101000101 ,
b101000100 %
1*
#325000
0*
#325500
b101000110 ,
b101000101 %
1*
#326000
0*
#326500
b101000111 ,
b101000110 %
1*
#327000
0*
#327500
b101001000 ,
b101000111 %
1*
#328000
0*
#328500
b101001001 ,
b101001000 %
1*
#329000
0*
#329500
b101001010 ,
b101001001 %
1*
#330000
0*
#330500
b101001011 ,
b101001010 %
1*
#331000
0*
#331500
b101001100 ,
b101001011 %
1*
#332000
0*
#332500
b101001101 ,
b101001100 %
1*
#333000
0*
#333500
b101001110 ,
b101001101 %
1*
#334000
0*
#334500
b101001111 ,
b101001110 %
1*
#335000
0*
#335500
b101010000 ,
b101001111 %
1*
#336000
0*
#336500
b101010001 ,
b101010000 %
1*
#337000
0*
#337500
b101010010 ,
b101010001 %
1*
#338000
0*
#338500
b101010011 ,
b101010010 %
1*
#339000
0*
#339500
b101010100 ,
b101010011 %
1*
#340000
0*
#340500
b101010101 ,
b101010100 %
1*
#341000
0*
#341500
b101010110 ,
b101010101 %
1*
#342000
0*
#342500
b101010111 ,
b101010110 %
1*
#343000
0*
#343500
b101011000 ,
b101010111 %
1*
#344000
0*
#344500
b101011001 ,
b101011000 %
1*
#345000
0*
#345500
b101011010 ,
b101011001 %
1*
#346000
0*
#346500
b101011011 ,
b101011010 %
1*
#347000
0*
#347500
b101011100 ,
b101011011 %
1*
#348000
0*
#348500
b101011101 ,
b101011100 %
1*
#349000
0*
#349500
b101011110 ,
b101011101 %
1*
#350000
0*
#350500
b101011111 ,
b101011110 %
1*
#351000
0*
#351500
b101100000 ,
b101011111 %
1*
#352000
0*
#352500
b101100001 ,
b101100000 %
1*
#353000
0*
#353500
b101100010 ,
b101100001 %
1*
#354000
0*
#354500
b101100011 ,
b101100010 %
1*
#355000
0*
#355500
b101100100 ,
b101100011 %
1*
#356000
0*
#356500
b101100101 ,
b101100100 %
1*
#357000
0*
#357500
b101100110 ,
b101100101 %
1*
#358000
0*
#358500
b101100111 ,
b101100110 %
1*
#359000
0*
#359500
b101101000 ,
b101100111 %
1*
#360000
0*
#360500
b101101001 ,
b101101000 %
1*
#361000
0*
#361500
b101101010 ,
b101101001 %
1*
#362000
0*
#362500
b101101011 ,
b101101010 %
1*
#363000
0*
#363500
b101101100 ,
b101101011 %
1*
#364000
0*
#364500
b101101101 ,
b101101100 %
1*
#365000
0*
#365500
b101101110 ,
b101101101 %
1*
#366000
0*
#366500
b101101111 ,
b101101110 %
1*
#367000
0*
#367500
b101110000 ,
b101101111 %
1*
#368000
0*
#368500
b101110001 ,
b101110000 %
1*
#369000
0*
#369500
b101110010 ,
b101110001 %
1*
#370000
0*
#370500
b101110011 ,
b101110010 %
1*
#371000
0*
#371500
b101110100 ,
b101110011 %
1*
#372000
0*
#372500
b101110101 ,
b101110100 %
1*
#373000
0*
#373500
b101110110 ,
b101110101 %
1*
#374000
0*
#374500
b101110111 ,
b101110110 %
1*
#375000
0*
#375500
b101111000 ,
b101110111 %
1*
#376000
0*
#376500
b101111001 ,
b101111000 %
1*
#377000
0*
#377500
b101111010 ,
b101111001 %
1*
#378000
0*
#378500
b101111011 ,
b101111010 %
1*
#379000
0*
#379500
b101111100 ,
b101111011 %
1*
#380000
0*
#380500
b101111101 ,
b101111100 %
1*
#381000
0*
#381500
b101111110 ,
b101111101 %
1*
#382000
0*
#382500
b101111111 ,
b101111110 %
1*
#383000
0*
#383500
b110000000 ,
b101111111 %
1*
#384000
0*
#384500
b110000001 ,
b110000000 %
1*
#385000
0*
#385500
b110000010 ,
b110000001 %
1*
#386000
0*
#386500
b110000011 ,
b110000010 %
1*
#387000
0*
#387500
b110000100 ,
b110000011 %
1*
#388000
0*
#388500
b110000101 ,
b110000100 %
1*
#389000
0*
#389500
b110000110 ,
b110000101 %
1*
#390000
0*
#390500
b110000111 ,
b110000110 %
1*
#391000
0*
#391500
b110001000 ,
b110000111 %
1*
#392000
0*
#392500
b110001001 ,
b110001000 %
1*
#393000
0*
#393500
b110001010 ,
b110001001 %
1*
#394000
0*
#394500
b110001011 ,
b110001010 %
1*
#395000
0*
#395500
b110001100 ,
b110001011 %
1*
#396000
0*
#396500
b110001101 ,
b110001100 %
1*
#397000
0*
#397500
b110001110 ,
b110001101 %
1*
#398000
0*
#398500
b110001111 ,
b110001110 %
1*
#399000
0*
#399500
b110010000 ,
b110001111 %
1*
#400000
0*
#400500
b110010001 ,
b110010000 %
1*
#401000
0*
#401500
b110010010 ,
b110010001 %
1*
#402000
0*
#402500
b110010011 ,
b110010010 %
1*
#403000
0*
#403500
b110010100 ,
b110010011 %
1*
#404000
0*
#404500
b110010101 ,
b110010100 %
1*
#405000
0*
#405500
b110010110 ,
b110010101 %
1*
#406000
0*
#406500
b110010111 ,
b110010110 %
1*
#407000
0*
#407500
b110011000 ,
b110010111 %
1*
#408000
0*
#408500
b110011001 ,
b110011000 %
1*
#409000
0*
#409500
b110011010 ,
b110011001 %
1*
#410000
0*
#410500
b110011011 ,
b110011010 %
1*
#411000
0*
#411500
b110011100 ,
b110011011 %
1*
#412000
0*
#412500
b110011101 ,
b110011100 %
1*
#413000
0*
#413500
b110011110 ,
b110011101 %
1*
#414000
0*
#414500
b110011111 ,
b110011110 %
1*
#415000
0*
#415500
b110100000 ,
b110011111 %
1*
#416000
0*
#416500
b110100001 ,
b110100000 %
1*
#417000
0*
#417500
b110100010 ,
b110100001 %
1*
#418000
0*
#418500
b110100011 ,
b110100010 %
1*
#419000
0*
#419500
b110100100 ,
b110100011 %
1*
#420000
0*
#420500
b110100101 ,
b110100100 %
1*
#421000
0*
#421500
b110100110 ,
b110100101 %
1*
#422000
0*
